intercessions/__init__.py
intercessions/terminal.py
intercessions/terminalsize.py
intercessions/win32.py
intercessions-1.1.8.dist-info/LICENSE
intercessions-1.1.8.dist-info/METADATA
intercessions-1.1.8.dist-info/WHEEL
intercessions-1.1.8.dist-info/top_level.txt
intercessions-1.1.8.dist-info/RECORD
