Metadata-Version: 2.1
Name: intercessions
Version: 1.1.8
Summary: A blessings polyfill for the windows command line
Home-page: https://github.com/Eeems/intercessions
Author: Nathaniel van Diepen
Author-email: eeems13@gmail.com
License: MIT
Keywords: terminal tty curses ncurses formatting style color console blessings blessed
Platform: UNKNOWN
Classifier: Development Status :: 7 - Inactive
Classifier: Environment :: Console
Classifier: Environment :: Console :: Curses
Classifier: Intended Audience :: Developers
Classifier: License :: OSI Approved :: MIT License
Classifier: Programming Language :: Python :: 3
Classifier: Programming Language :: Python :: 3.7
Classifier: Programming Language :: Python :: 3.8
Classifier: Programming Language :: Python :: 3.9
Classifier: Programming Language :: Python :: 3.10
Classifier: Topic :: Software Development :: Libraries
Classifier: Topic :: Software Development :: User Interfaces
Classifier: Topic :: Terminals
License-File: LICENSE
Requires-Dist: colorama
Provides-Extra: dev
Requires-Dist: pipreqs ; extra == 'dev'
Provides-Extra: optional
Requires-Dist: blessings ; extra == 'optional'
